{"pageNumber":371,"ayahs":[{"number":3016,"numberInSurah":84,"text":"وَٱجْعَل لِّى لِسَانَ صِدْقٍۢ فِى ٱلْءَاخِرِينَ","juz":19,"hizbQuarter":148,"page":371,"surah":{"number":26,"name":"سُورَةُ الشُّعَرَاءِ","englishName":"Ash-Shu'araa"}},{"number":3017,"numberInSurah":85,"text":"وَٱجْعَلْنِى مِن وَرَثَةِ جَنَّةِ ٱلنَّعِيمِ","juz":19,"hizbQuarter":148,"page":371,"surah":{"number":26,"name":"سُورَةُ الشُّعَرَاءِ","englishName":"Ash-Shu'araa"}},{"number":3018,"numberInSurah":86,"text":"وَٱغْفِرْ لِأَبِىٓ إِنَّهُۥ كَانَ مِنَ ٱلضَّآلِّينَ","juz":19,"hizbQuarter":148,"page":371,"surah":{"number":26,"name":"سُورَةُ الشُّعَرَاءِ","englishName":"Ash-Shu'araa"}},{"number":3019,"numberInSurah":87,"text":"وَلَا تُخْزِنِى يَوْمَ يُبْعَثُونَ","juz":19,"hizbQuarter":148,"page":371,"surah":{"number":26,"name":"سُورَةُ الشُّعَرَاءِ","englishName":"Ash-Shu'araa"}},{"number":3020,"numberInSurah":88,"text":"يَوْمَ لَا يَنفَعُ مَالٌۭ وَلَا بَنُونَ","juz":19,"hizbQuarter":148,"page":371,"surah":{"number":26,"name":"سُورَةُ الشُّعَرَاءِ","englishName":"Ash-Shu'araa"}},{"number":3021,"numberInSurah":89,"text":"إِلَّا مَنْ أَتَى ٱللَّهَ بِقَلْبٍۢ سَلِيمٍۢ","juz":19,"hizbQuarter":148,"page":371,"surah":{"number":26,"name":"سُورَةُ الشُّعَرَاءِ","englishName":"Ash-Shu'araa"}},{"number":3022,"numberInSurah":90,"text":"وَأُزْلِفَتِ ٱلْجَنَّةُ لِلْمُتَّقِينَ","juz":19,"hizbQuarter":148,"page":371,"surah":{"number":26,"name":"سُورَةُ الشُّعَرَاءِ","englishName":"Ash-Shu'araa"}},{"number":3023,"numberInSurah":91,"text":"وَبُرِّزَتِ ٱلْجَحِيمُ لِلْغَاوِينَ","juz":19,"hizbQuarter":148,"page":371,"surah":{"number":26,"name":"سُورَةُ الشُّعَرَاءِ","englishName":"Ash-Shu'araa"}},{"number":3024,"numberInSurah":92,"text":"وَقِيلَ لَهُمْ أَيْنَ مَا كُنتُمْ تَعْبُدُونَ","juz":19,"hizbQuarter":148,"page":371,"surah":{"number":26,"name":"سُورَةُ الشُّعَرَاءِ","englishName":"Ash-Shu'araa"}},{"number":3025,"numberInSurah":93,"text":"مِن دُونِ ٱللَّهِ هَلْ يَنصُرُونَكُمْ أَوْ يَنتَصِرُونَ","juz":19,"hizbQuarter":148,"page":371,"surah":{"number":26,"name":"سُورَةُ الشُّعَرَاءِ","englishName":"Ash-Shu'araa"}},{"number":3026,"numberInSurah":94,"text":"فَكُبْكِبُوا۟ فِيهَا هُمْ وَٱلْغَاوُۥنَ","juz":19,"hizbQuarter":148,"page":371,"surah":{"number":26,"name":"سُورَةُ الشُّعَرَاءِ","englishName":"Ash-Shu'araa"}},{"number":3027,"numberInSurah":95,"text":"وَجُنُودُ إِبْلِيسَ أَجْمَعُونَ","juz":19,"hizbQuarter":148,"page":371,"surah":{"number":26,"name":"سُورَةُ الشُّعَرَاءِ","englishName":"Ash-Shu'araa"}},{"number":3028,"numberInSurah":96,"text":"قَالُوا۟ وَهُمْ فِيهَا يَخْتَصِمُونَ","juz":19,"hizbQuarter":148,"page":371,"surah":{"number":26,"name":"سُورَةُ الشُّعَرَاءِ","englishName":"Ash-Shu'araa"}},{"number":3029,"numberInSurah":97,"text":"تَٱللَّهِ إِن كُنَّا لَفِى ضَلَٰلٍۢ مُّبِينٍ","juz":19,"hizbQuarter":148,"page":371,"surah":{"number":26,"name":"سُورَةُ الشُّعَرَاءِ","englishName":"Ash-Shu'araa"}},{"number":3030,"numberInSurah":98,"text":"إِذْ نُسَوِّيكُم بِرَبِّ ٱلْعَٰلَمِينَ","juz":19,"hizbQuarter":148,"page":371,"surah":{"number":26,"name":"سُورَةُ الشُّعَرَاءِ","englishName":"Ash-Shu'araa"}},{"number":3031,"numberInSurah":99,"text":"وَمَآ أَضَلَّنَآ إِلَّا ٱلْمُجْرِمُونَ","juz":19,"hizbQuarter":148,"page":371,"surah":{"number":26,"name":"سُورَةُ الشُّعَرَاءِ","englishName":"Ash-Shu'araa"}},{"number":3032,"numberInSurah":100,"text":"فَمَا لَنَا مِن شَٰفِعِينَ","juz":19,"hizbQuarter":148,"page":371,"surah":{"number":26,"name":"سُورَةُ الشُّعَرَاءِ","englishName":"Ash-Shu'araa"}},{"number":3033,"numberInSurah":101,"text":"وَلَا صَدِيقٍ حَمِيمٍۢ","juz":19,"hizbQuarter":148,"page":371,"surah":{"number":26,"name":"سُورَةُ الشُّعَرَاءِ","englishName":"Ash-Shu'araa"}},{"number":3034,"numberInSurah":102,"text":"فَلَوْ أَنَّ لَنَا كَرَّةًۭ فَنَكُونَ مِنَ ٱلْمُؤْمِنِينَ","juz":19,"hizbQuarter":148,"page":371,"surah":{"number":26,"name":"سُورَةُ الشُّعَرَاءِ","englishName":"Ash-Shu'araa"}},{"number":3035,"numberInSurah":103,"text":"إِنَّ فِى ذَٰلِكَ لَءَايَةًۭ ۖ وَمَا كَانَ أَكْثَرُهُم مُّؤْمِنِينَ","juz":19,"hizbQuarter":148,"page":371,"surah":{"number":26,"name":"سُورَةُ الشُّعَرَاءِ","englishName":"Ash-Shu'araa"}},{"number":3036,"numberInSurah":104,"text":"وَإِنَّ رَبَّكَ لَهُوَ ٱلْعَزِيزُ ٱلرَّحِيمُ","juz":19,"hizbQuarter":148,"page":371,"surah":{"number":26,"name":"سُورَةُ الشُّعَرَاءِ","englishName":"Ash-Shu'araa"}},{"number":3037,"numberInSurah":105,"text":"كَذَّبَتْ قَوْمُ نُوحٍ ٱلْمُرْسَلِينَ","juz":19,"hizbQuarter":148,"page":371,"surah":{"number":26,"name":"سُورَةُ الشُّعَرَاءِ","englishName":"Ash-Shu'araa"}},{"number":3038,"numberInSurah":106,"text":"إِذْ قَالَ لَهُمْ أَخُوهُمْ نُوحٌ أَلَا تَتَّقُونَ","juz":19,"hizbQuarter":148,"page":371,"surah":{"number":26,"name":"سُورَةُ الشُّعَرَاءِ","englishName":"Ash-Shu'araa"}},{"number":3039,"numberInSurah":107,"text":"إِنِّى لَكُمْ رَسُولٌ أَمِينٌۭ","juz":19,"hizbQuarter":148,"page":371,"surah":{"number":26,"name":"سُورَةُ الشُّعَرَاءِ","englishName":"Ash-Shu'araa"}},{"number":3040,"numberInSurah":108,"text":"فَٱتَّقُوا۟ ٱللَّهَ وَأَطِيعُونِ","juz":19,"hizbQuarter":148,"page":371,"surah":{"number":26,"name":"سُورَةُ الشُّعَرَاءِ","englishName":"Ash-Shu'araa"}},{"number":3041,"numberInSurah":109,"text":"وَمَآ أَسْـَٔلُكُمْ عَلَيْهِ مِنْ أَجْرٍ ۖ إِنْ أَجْرِىَ إِلَّا عَلَىٰ رَبِّ ٱلْعَٰلَمِينَ","juz":19,"hizbQuarter":148,"page":371,"surah":{"number":26,"name":"سُورَةُ الشُّعَرَاءِ","englishName":"Ash-Shu'araa"}},{"number":3042,"numberInSurah":110,"text":"فَٱتَّقُوا۟ ٱللَّهَ وَأَطِيعُونِ","juz":19,"hizbQuarter":148,"page":371,"surah":{"number":26,"name":"سُورَةُ الشُّعَرَاءِ","englishName":"Ash-Shu'araa"}},{"number":3043,"numberInSurah":111,"text":"۞ قَالُوٓا۟ أَنُؤْمِنُ لَكَ وَٱتَّبَعَكَ ٱلْأَرْذَلُونَ","juz":19,"hizbQuarter":149,"page":371,"surah":{"number":26,"name":"سُورَةُ الشُّعَرَاءِ","englishName":"Ash-Shu'araa"}}],"juz":19,"hizbQuarter":148,"surahs":{"26":{"number":26,"name":"سُورَةُ الشُّعَرَاءِ","englishName":"Ash-Shu'araa","englishNameTranslation":"The Poets","revelationType":"Meccan","numberOfAyahs":227}}}